easy_db_lib/__init__.py
easy_db_lib/database.py
easy_db_lib/row.py
easy_db_lib/table.py
tests/__init__.py
tests/test_module1.py
easy_db_lib-0.1.0.dist-info/METADATA
easy_db_lib-0.1.0.dist-info/WHEEL
easy_db_lib-0.1.0.dist-info/top_level.txt
easy_db_lib-0.1.0.dist-info/RECORD
