Metadata-Version: 2.1
Name: easy_db_lib
Version: 0.1.0
Summary: A very simple db lib.
Home-page: https://github.com/mr-comand/easy_db_lib
Author: Mr_comand
Classifier: Programming Language :: Python :: 3
Classifier: License :: OSI Approved :: MIT License
Classifier: Operating System :: OS Independent
Requires-Dist: psycopg2 ==2.9.9
